{
  "name": "Pays",
  "fields": [
    {
      "fieldName": "code",
      "fieldType": "String",
      "fieldValidateRules": ["required"]
    },
    {
      "fieldName": "nom",
      "fieldType": "String",
      "fieldValidateRules": ["required"]
    },
    {
      "fieldName": "description",
      "fieldType": "String"
    },
    {
      "fieldName": "logo",
      "fieldType": "byte[]",
      "fieldTypeBlobContent": "image"
    }
  ],
  "relationships": [
    {
      "relationshipType": "one-to-many",
      "otherEntityName": "ville",
      "otherEntityRelationshipName": "pays",
      "relationshipName": "ville",
      "otherEntityField": "nom"
    }
  ],
  "entityTableName": "pays",
  "dto": "mapstruct",
  "pagination": "pagination",
  "service": "serviceImpl",
  "jpaMetamodelFiltering": false,
  "fluentMethods": true,
  "readOnly": false,
  "embedded": false,
  "applications": "*",
  "changelogDate": "20210622115408"
}
